LICENSE
MANIFEST.in
README.md
dev-requirements.txt
setup.py
docs/Makefile
docs/make.bat
docs/requirements.txt
docs/source/conf.py
docs/source/index.md
docs/source/options.md
docs/source/quickstart.md
docs/source/troubleshooting.md
docs/source/_static/authorization_area.png
docs/source/_static/block_user_failed_logins.png
docs/source/_static/change_password_self.png
docs/source/_static/change_password_user.png
docs/source/_static/login-two-factor-auth.png
docs/source/_static/native_auth_flow.png
docs/source/_static/signup-two-factor-auth.png
docs/source/_static/wrong_signup.png
jupyterhub_tmpnativeauthenticator.egg-info/PKG-INFO
jupyterhub_tmpnativeauthenticator.egg-info/SOURCES.txt
jupyterhub_tmpnativeauthenticator.egg-info/dependency_links.txt
jupyterhub_tmpnativeauthenticator.egg-info/requires.txt
jupyterhub_tmpnativeauthenticator.egg-info/top_level.txt
nativeauthenticator/__init__.py
nativeauthenticator/common-credentials.txt
nativeauthenticator/handlers.py
nativeauthenticator/nativeauthenticator.py
nativeauthenticator/orm.py
nativeauthenticator/crypto/__init__.py
nativeauthenticator/crypto/crypto.py
nativeauthenticator/crypto/encoding.py
nativeauthenticator/crypto/signing.py
nativeauthenticator/templates/authorization-area.html
nativeauthenticator/templates/change-password-admin.html
nativeauthenticator/templates/change-password.html
nativeauthenticator/templates/my_message.html
nativeauthenticator/templates/native-login.html
nativeauthenticator/templates/page.html
nativeauthenticator/templates/signup.html
nativeauthenticator/tests/__init__.py
nativeauthenticator/tests/test_authenticator.py
nativeauthenticator/tests/test_orm.py