Metadata-Version: 2.1
Name: jupyterhub-tmpnativeauthenticator
Version: 1.0.1
Summary: JupyterHub Native Authenticator with tmp login
Home-page: https://github.com/Gorbacheb/tmpnativeauthenticator
Author: Vladimir Nedugov
Author-email: MegaRs1@yandex.ru
License: MIT
License-File: LICENSE
